varformat/__init__.py
varformat/formats.py
varformat-1.0.0.dist-info/LICENSE.txt
varformat-1.0.0.dist-info/METADATA
varformat-1.0.0.dist-info/WHEEL
varformat-1.0.0.dist-info/top_level.txt
varformat-1.0.0.dist-info/RECORD
