Metadata-Version: 2.1
Name: varformat
Version: 1.0.0
Summary: Format an parse strings with ${variables} of any syntax.
Author: Anna Zhukova
Project-URL: Repository, https://github.com/bindreams/varformat
Project-URL: Issues, https://github.com/bindreams/varformat/issues
Keywords: string,interpolation,variable,shell,format,parse
Classifier: Development Status :: 5 - Production/Stable
Classifier: License :: OSI Approved :: Apache Software License
Classifier: Natural Language :: English
Classifier: Operating System :: OS Independent
Classifier: Programming Language :: Python
Classifier: Programming Language :: Python :: 3.8
Classifier: Programming Language :: Python :: 3.9
Classifier: Programming Language :: Python :: 3.10
Classifier: Programming Language :: Python :: 3.11
Classifier: Programming Language :: Python :: 3.12
Classifier: Topic :: Text Processing
Classifier: Typing :: Typed
Requires-Python: >=3.8
License-File: LICENSE.txt
Requires-Dist: regex
Requires-Dist: typing-extensions ; python_version < "3.10"
